nonlinshrink/__init__.py
nonlinshrink/nonlinshrink.py
non_linear_shrinkage-1.0.0.dist-info/LICENSE.txt
non_linear_shrinkage-1.0.0.dist-info/METADATA
non_linear_shrinkage-1.0.0.dist-info/WHEEL
non_linear_shrinkage-1.0.0.dist-info/top_level.txt
non_linear_shrinkage-1.0.0.dist-info/RECORD
