Metadata-Version: 2.1
Name: non-linear-shrinkage
Version: 1.0.0
Summary: Non-Linear Shrinkage Estimator from Ledoit and Wolf (2018) 
Home-page: https://github.com/shoemakerdr/analytic_shrinkage
License: UNKNOWN
Platform: UNKNOWN
Classifier: Programming Language :: Python :: 3
Classifier: License :: OSI Approved :: MIT License
Classifier: Operating System :: OS Independent
Requires-Python: >=3.6
License-File: LICENSE.txt
Requires-Dist: numpy
